mydocstring/__init__.py
mydocstring/command.py
mydocstring/docstring.py
mydocstring/extract.py
mydocstring/parse.py
mydocstring/version.py
mydocstring/templates/google_docstring.md
mydocstring-0.2.7.dist-info/DESCRIPTION.rst
mydocstring-0.2.7.dist-info/METADATA
mydocstring-0.2.7.dist-info/RECORD
mydocstring-0.2.7.dist-info/WHEEL
mydocstring-0.2.7.dist-info/entry_points.txt
mydocstring-0.2.7.dist-info/metadata.json
mydocstring-0.2.7.dist-info/top_level.txt
