Metadata-Version: 2.0
Name: mydocstring
Version: 0.2.7
Summary: A tool for extracting and converting Google-style docstrings to
Home-page: http://github.com/ooreilly/mydocstring
Author: Ossian O'Reilly
Author-email: UNKNOWN
License: MIT
Platform: UNKNOWN
Requires-Dist: mako
Requires-Dist: docopt
